dagrunner/__init__.py
dagrunner/dag.py
dagrunner/task.py
dagrunner/libs/__init__.py
dagrunner/libs/constants.py
dagrunner/utils/__init__.py
dagrunner/utils/logger.py
dagrunner-0.0.6.dist-info/LICENSE
dagrunner-0.0.6.dist-info/METADATA
dagrunner-0.0.6.dist-info/WHEEL
dagrunner-0.0.6.dist-info/top_level.txt
dagrunner-0.0.6.dist-info/RECORD
