Metadata-Version: 2.1
Name: dagrunner
Version: 0.0.6
Summary: Run tasks as per dags
Author: Jatin Lal
Author-email: jatinlal1994@gmail.com
Keywords: python,dag
Classifier: Development Status :: 2 - Pre-Alpha
Classifier: Intended Audience :: Developers
Classifier: Programming Language :: Python :: 3
Classifier: Operating System :: Unix
Classifier: Operating System :: MacOS :: MacOS X
Classifier: Operating System :: Microsoft :: Windows
License-File: LICENSE
Requires-Dist: networkx
